pyband2/__init__.py
pyband2/auth.py
pyband2/client.py
pyband2/constant.py
pyband2/data.py
pyband2/message.py
pyband2/obi.py
pyband2/transaction.py
pyband2/utils.py
pyband2/wallet.py
pyband2-0.0.2.dist-info/METADATA
pyband2-0.0.2.dist-info/WHEEL
pyband2-0.0.2.dist-info/top_level.txt
pyband2-0.0.2.dist-info/RECORD
