Metadata-Version: 2.1
Name: pyband2
Version: 0.0.2
Summary: Python library for BandChain
Home-page: https://github.com/bandprotocol/bandchain
Author: Band Protocol
Author-email: dev@bandprotocol.com
License: MIT
Keywords: BAND,BLOCKCHAIN,ORACLE
Platform: UNKNOWN
Classifier: Development Status :: 3 - Alpha
Classifier: Intended Audience :: Developers
Classifier: License :: OSI Approved :: MIT License
Classifier: Programming Language :: Python :: 3
Classifier: Programming Language :: Python :: 3.6
Classifier: Programming Language :: Python :: 3.7
Classifier: Programming Language :: Python :: 3.8
Requires-Dist: requests
Requires-Dist: dacite
Requires-Dist: bech32
Requires-Dist: bip32
Requires-Dist: ecdsa
Requires-Dist: mnemonic
